dell_unity_mcp_server-1.0.2.dist-info/licenses/LICENSE
unity_mcp/__init__.py
unity_mcp/api_client.py
unity_mcp/config.py
unity_mcp/exceptions.py
unity_mcp/http_server.py
unity_mcp/logging_config.py
unity_mcp/main.py
unity_mcp/py.typed
unity_mcp/server.py
unity_mcp/tool_generator.py
dell_unity_mcp_server-1.0.2.dist-info/METADATA
dell_unity_mcp_server-1.0.2.dist-info/WHEEL
dell_unity_mcp_server-1.0.2.dist-info/entry_points.txt
dell_unity_mcp_server-1.0.2.dist-info/top_level.txt
dell_unity_mcp_server-1.0.2.dist-info/RECORD
