Metadata-Version: 2.4
Name: dell-unity-mcp-server
Version: 1.0.2
Summary: Model Context Protocol (MCP) server for Dell Unity Storage Systems
Author-email: Dell Technologies <support@dell.com>
Maintainer-email: Dell Technologies <support@dell.com>
License-Expression: MIT
Project-URL: Homepage, https://github.com/sachdev27/dell-unity-mcp-server
Project-URL: Documentation, https://github.com/sachdev27/dell-unity-mcp-server#readme
Project-URL: Repository, https://github.com/sachdev27/dell-unity-mcp-server.git
Project-URL: Issues, https://github.com/sachdev27/dell-unity-mcp-server/issues
Keywords: dell,unity,storage,mcp,model-context-protocol,ai,llm,claude,automation
Classifier: Development Status :: 4 - Beta
Classifier: Intended Audience :: Developers
Classifier: Intended Audience :: System Administrators
Classifier: Operating System :: OS Independent
Classifier: Programming Language :: Python :: 3
Classifier: Programming Language :: Python :: 3.10
Classifier: Programming Language :: Python :: 3.11
Classifier: Programming Language :: Python :: 3.12
Classifier: Programming Language :: Python :: 3.13
Classifier: Topic :: System :: Systems Administration
Classifier: Topic :: Software Development :: Libraries :: Python Modules
Classifier: Typing :: Typed
Requires-Python: >=3.10
License-File: LICENSE
Requires-Dist: mcp>=1.0.0
Requires-Dist: httpx>=0.25.0
Requires-Dist: pydantic>=2.0.0
Requires-Dist: pydantic-settings>=2.0.0
Requires-Dist: python-dotenv>=1.0.0
Requires-Dist: pyyaml>=6.0
Requires-Dist: uvicorn>=0.24.0
Provides-Extra: dev
Requires-Dist: pytest>=7.0.0; extra == "dev"
Requires-Dist: pytest-asyncio>=0.21.0; extra == "dev"
Requires-Dist: pytest-cov>=4.0.0; extra == "dev"
Requires-Dist: mypy>=1.0.0; extra == "dev"
Requires-Dist: types-PyYAML>=6.0.0; extra == "dev"
Requires-Dist: ruff>=0.1.0; extra == "dev"
Requires-Dist: black>=23.0.0; extra == "dev"
Requires-Dist: pre-commit>=3.0.0; extra == "dev"
Dynamic: license-file
